yta_multimedia_ffmpeg_handler/__init__.py
yta_multimedia_ffmpeg_handler/enums.py
yta_multimedia_ffmpeg_handler-0.0.5.dist-info/LICENSE
yta_multimedia_ffmpeg_handler-0.0.5.dist-info/METADATA
yta_multimedia_ffmpeg_handler-0.0.5.dist-info/WHEEL
yta_multimedia_ffmpeg_handler-0.0.5.dist-info/RECORD
